setup.py
dochap/__init__.py
dochap/combiner.py
dochap/conf.py
dochap/db_creator.py
dochap/dochap.py
dochap/domains_to_exons.py
dochap/gbk_parser.py
dochap/interface.py
dochap/parse_output.py
dochap/parser.py
dochap/progressbar.py
dochap/setup.py
dochap/test.py
dochap/ucsc_downloader.py
dochap/ucsc_parser.py
dochap/updater.py
dochap/visualizer.py
dochap.egg-info/PKG-INFO
dochap.egg-info/SOURCES.txt
dochap.egg-info/dependency_links.txt
dochap.egg-info/not-zip-safe
dochap.egg-info/requires.txt
dochap.egg-info/top_level.txt